{
    "difficulty": {
        "level": 2
    },
    "frequency": 0,
    "is_favor": false,
    "paid_only": false,
    "progress": 0,
    "stat": {
        "frontend_question_id": 7,
        "is_new_question": false,
        "question__article__has_video_solution": true,
        "question__article__live": true,
        "question__article__slug": "reverse-integer",
        "question__hide": false,
        "question__title": "Reverse Integer",
        "question__title_slug": "reverse-integer",
        "question_id": 7,
        "total_acs": 2682466,
        "total_submitted": 9696862
    },
    "status": null
}
